scrapy_proxy_headers/__init__.py
scrapy_proxy_headers/agent.py
scrapy_proxy_headers/download_handler.py
scrapy_proxy_headers-0.1.4.dist-info/LICENSE
scrapy_proxy_headers-0.1.4.dist-info/METADATA
scrapy_proxy_headers-0.1.4.dist-info/WHEEL
scrapy_proxy_headers-0.1.4.dist-info/top_level.txt
scrapy_proxy_headers-0.1.4.dist-info/RECORD
