Metadata-Version: 2.1
Name: scrapy-proxy-headers
Version: 0.1.4
Summary: Add custom proxy headers to HTTPS requests in Scrapy
Author-email: ProxyMesh <support@proxymesh.com>
Project-URL: Homepage, https://github.com/proxymesh/scrapy-proxy-headers
Project-URL: Changelog, https://github.com/proxymesh/scrapy-proxy-headers/commits/main/
Project-URL: Issues, https://github.com/proxymesh/scrapy-proxy-headers/issues
Classifier: Programming Language :: Python :: 3
Classifier: Operating System :: OS Independent
Classifier: License :: OSI Approved :: BSD License
Classifier: Intended Audience :: Developers
Classifier: Topic :: Internet :: WWW/HTTP
Classifier: Topic :: Software Development :: Libraries :: Python Modules
Requires-Python: >=3.8
License-File: LICENSE
